mc_server_status/__init__.py
mc_server_status/format_data.py
mc_server_status/handling_requests.py
mc_server_status/main.py
mcscan-3.0.dist-info/LICENSE
mcscan-3.0.dist-info/METADATA
mcscan-3.0.dist-info/WHEEL
mcscan-3.0.dist-info/entry_points.txt
mcscan-3.0.dist-info/top_level.txt
mcscan-3.0.dist-info/RECORD
