Metadata-Version: 2.1
Name: mcscan
Version: 3.0
Summary: A cli application to fetch data from your favourite minecraft server.
Home-page: https://github.com/Moritz344/mcstatus-cli
Author: Moritz Maier
Author-email: moritzmaier353@gmail.com
License: UNKNOWN
Platform: UNKNOWN
Classifier: Programming Language :: Python :: 3
Classifier: License :: OSI Approved :: MIT License
Classifier: Operating System :: OS Independent
Requires-Python: >=3.7
License-File: LICENSE
Requires-Dist: requests
Requires-Dist: rich
Requires-Dist: termcolor
